Avalara/SDK/api_client.py
Avalara/SDK/configuration.py
Avalara/SDK/exceptions.py
Avalara/SDK/model_utils.py
Avalara/SDK/rest.py
Avalara/SDK/api/A1099/V2/companies_w9_api.py
Avalara/SDK/api/A1099/V2/forms1099_api.py
Avalara/SDK/api/A1099/V2/forms_w9_api.py
Avalara/SDK/api/A1099/V2/issuers1099_api.py
Avalara/SDK/api/A1099/V2/jobs_api.py
Avalara/SDK/api/EInvoicing/V1/data_input_fields_api.py
Avalara/SDK/api/EInvoicing/V1/documents_api.py
Avalara/SDK/api/EInvoicing/V1/interop_api.py
Avalara/SDK/api/EInvoicing/V1/mandates_api.py
Avalara/SDK/api/EInvoicing/V1/subscriptions_api.py
Avalara/SDK/api/EInvoicing/V1/tax_identifiers_api.py
Avalara/SDK/api/EInvoicing/V1/trading_partners_api.py
Avalara/SDK/models/A1099/V2/authorized_api_request_model.py
Avalara/SDK/models/A1099/V2/authorized_api_request_v2_data_model.py
Avalara/SDK/models/A1099/V2/company_base.py
Avalara/SDK/models/A1099/V2/company_create_update_request_model.py
Avalara/SDK/models/A1099/V2/company_request.py
Avalara/SDK/models/A1099/V2/company_response.py
Avalara/SDK/models/A1099/V2/covered_individual.py
Avalara/SDK/models/A1099/V2/create_and_send_w9_form_email_request.py
Avalara/SDK/models/A1099/V2/create_company_request.py
Avalara/SDK/models/A1099/V2/create_issuer_request.py
Avalara/SDK/models/A1099/V2/create_w9_form201_response.py
Avalara/SDK/models/A1099/V2/create_w9_form_request.py
Avalara/SDK/models/A1099/V2/entry_status_response.py
Avalara/SDK/models/A1099/V2/error_model.py
Avalara/SDK/models/A1099/V2/error_response.py
Avalara/SDK/models/A1099/V2/error_response_item.py
Avalara/SDK/models/A1099/V2/form1042_s.py
Avalara/SDK/models/A1099/V2/form1095_b.py
Avalara/SDK/models/A1099/V2/form1095_c.py
Avalara/SDK/models/A1099/V2/form1099_base.py
Avalara/SDK/models/A1099/V2/form1099_div.py
Avalara/SDK/models/A1099/V2/form1099_int.py
Avalara/SDK/models/A1099/V2/form1099_k.py
Avalara/SDK/models/A1099/V2/form1099_list_request.py
Avalara/SDK/models/A1099/V2/form1099_misc.py
Avalara/SDK/models/A1099/V2/form1099_nec.py
avalara_sdk-25.11.1.dist-info/METADATA
avalara_sdk-25.11.1.dist-info/WHEEL
avalara_sdk-25.11.1.dist-info/top_level.txt
avalara_sdk-25.11.1.dist-info/RECORD
