Metadata-Version: 2.4
Name: Avalara.SDK
Version: 25.11.1
Summary: Avalara 1099 &amp; W-9 API Definition
Home-page: 
Author: Developer Support
Author-email: support@avalara.com
License: Apache 2.0
Keywords: OpenAPI,OpenAPI-Generator,Avalara 1099 & W-9 API Definition
Requires-Dist: urllib3<2.1.0,>=1.25.3
Requires-Dist: python-dateutil
Requires-Dist: pydantic>=2
Dynamic: author
Dynamic: author-email
Dynamic: description
Dynamic: description-content-type
Dynamic: keywords
Dynamic: license
Dynamic: requires-dist
Dynamic: summary
